rc_assign_2021_sloan.py
rc_assign_2021_sloan-0.0.1.dist-info/LICENSE.txt
rc_assign_2021_sloan-0.0.1.dist-info/METADATA
rc_assign_2021_sloan-0.0.1.dist-info/WHEEL
rc_assign_2021_sloan-0.0.1.dist-info/top_level.txt
rc_assign_2021_sloan-0.0.1.dist-info/RECORD
